introspection/__init__.py
introspection/apps.py
introspection/colors.py
introspection/const.py
introspection/model.py
introspection/utils.py
introspection/inspector/__init__.py
introspection/inspector/inspector.py
introspection/management/__init__.py
introspection/management/commands/__init__.py
introspection/management/commands/inspectapp.py
introspection/management/commands/inspectmodel.py
django_introspection-0.9.0.dist-info/LICENSE
django_introspection-0.9.0.dist-info/METADATA
django_introspection-0.9.0.dist-info/WHEEL
django_introspection-0.9.0.dist-info/top_level.txt
django_introspection-0.9.0.dist-info/zip-safe
django_introspection-0.9.0.dist-info/RECORD
