Metadata-Version: 2.1
Name: django-introspection
Version: 0.9.0
Summary: Introspection tools for Django
Home-page: https://github.com/synw/django-introspection
Author: synw
Author-email: synwe@yahoo.com
License: MIT
Keywords: Python Django
Classifier: Development Status :: 4 - Beta
Classifier: Intended Audience :: Developers
Classifier: License :: OSI Approved :: MIT License
Classifier: Natural Language :: English
Classifier: Programming Language :: Python :: 3
Classifier: Programming Language :: Python :: 3.6
Classifier: Programming Language :: Python :: 3.7
Classifier: Programming Language :: Python :: 3.8
Classifier: Framework :: Django
Classifier: Framework :: Django :: 2.2
Classifier: Framework :: Django :: 3.0
Classifier: Framework :: Django :: 4.0
Provides-Extra: dev
License-File: LICENSE
